streamlit_img_label/__init__.py
streamlit_img_label/annotation.py
streamlit_img_label/manage.py
streamlit_img_label/frontend/.gitignore
streamlit_img_label/frontend/.prettierrc
streamlit_img_label/frontend/package.json
streamlit_img_label/frontend/tsconfig.json
streamlit_img_label/frontend/build/asset-manifest.json
streamlit_img_label/frontend/build/bootstrap.min.css
streamlit_img_label/frontend/build/index.html
streamlit_img_label/frontend/build/precache-manifest.b5513ea1aa30f2a517dcf8a664ec6a82.js
streamlit_img_label/frontend/build/service-worker.js
streamlit_img_label/frontend/build/static/css/main.00623a57.chunk.css
streamlit_img_label/frontend/build/static/css/main.00623a57.chunk.css.map
streamlit_img_label/frontend/build/static/js/2.b19543fd.chunk.js
streamlit_img_label/frontend/build/static/js/2.b19543fd.chunk.js.LICENSE.txt
streamlit_img_label/frontend/build/static/js/2.b19543fd.chunk.js.map
streamlit_img_label/frontend/build/static/js/main.25f4a86d.chunk.js
streamlit_img_label/frontend/build/static/js/main.25f4a86d.chunk.js.map
streamlit_img_label/frontend/build/static/js/runtime-main.4a6ba311.js
streamlit_img_label/frontend/build/static/js/runtime-main.4a6ba311.js.map
streamlit_img_label/frontend/public/bootstrap.min.css
streamlit_img_label/frontend/public/index.html
streamlit_img_label/frontend/src/StreamlitImgLabel.module.css
streamlit_img_label/frontend/src/StreamlitImgLabel.tsx
streamlit_img_label/frontend/src/index.tsx
streamlit_img_label/frontend/src/react-app-env.d.ts
streamlit_img_label-0.1.1.dist-info/LICENSE
streamlit_img_label-0.1.1.dist-info/METADATA
streamlit_img_label-0.1.1.dist-info/WHEEL
streamlit_img_label-0.1.1.dist-info/top_level.txt
streamlit_img_label-0.1.1.dist-info/RECORD
