Metadata-Version: 2.1
Name: streamlit_img_label
Version: 0.1.1
Summary: Streamlit Image Annotation
Home-page: https://github.com/lit26/streamlit-img-label
Author: Tianning Li
Author-email: ltianningli@gmail.com
License: UNKNOWN
Platform: UNKNOWN
Requires-Python: >=3.6
